Metadata-Version: 2.1
Name: odoo12-addon-shopinvader-assortment
Version: 12.0.1.1.2
Summary: Shopinvader Assortment
Home-page: http://github.com/shopinvader/odoo-shopinvader
Author: ACSONE SA/NV
License: AGPL-3
Platform: UNKNOWN
Classifier: Programming Language :: Python
Classifier: Framework :: Odoo
Classifier: License :: OSI Approved :: GNU Affero General Public License v3
Requires-Python: >=3.5
Requires-Dist: odoo12-addon-product-assortment
Requires-Dist: odoo12-addon-shopinvader
Requires-Dist: odoo12-addon-shopinvader-search-engine
Requires-Dist: odoo (<12.1dev,>=12.0a)
